<Gesture Name="zigzag"><Point T="0" X="875" Y="826" /><Point T="0" X="548" Y="0" /><Point T="0" X="548" Y="0" /><Point T="0" X="548" Y="0" /><Point T="0" X="557" Y="0" /><Point T="0" X="580" Y="0" /><Point T="0" X="594" Y="85" /><Point T="0" X="603" Y="142" /><Point T="0" X="595" Y="243" /><Point T="0" X="593" Y="212" /><Point T="0" X="592" Y="189" /><Point T="0" X="597" Y="170" /><Point T="0" X="596" Y="154" /><Point T="0" X="594" Y="142" /><Point T="0" X="583" Y="131" /><Point T="0" X="588" Y="121" /><Point T="0" X="598" Y="113" /><Point T="0" X="610" Y="136" /><Point T="0" X="620" Y="203" /><Point T="0" X="620" Y="203" /><Point T="0" X="949" Y="849" /><Point T="0" X="748" Y="0" /><Point T="0" X="848" Y="0" /><Point T="0" X="882" Y="0" /><Point T="0" X="865" Y="24" /><Point T="0" X="869" Y="38" /><Point T="0" X="872" Y="102" /><Point T="0" X="854" Y="209" /><Point T="0" X="841" Y="289" /><Point T="0" X="845" Y="351" /><Point T="0" X="846" Y="434" /><Point T="0" X="842" Y="502" /><Point T="0" X="823" Y="531" /><Point T="0" X="823" Y="497" /><Point T="0" X="828" Y="516" /><Point T="0" X="838" Y="555" /><Point T="0" X="847" Y="597" /><Point T="0" X="853" Y="612" /><Point T="0" X="861" Y="644" /><Point T="0" X="867" Y="672" /><Point T="0" X="871" Y="716" /><Point T="0" X="871" Y="716" /><Point T="0" X="1089" Y="260" /><Point T="0" X="1030" Y="441" /><Point T="0" X="1014" Y="531" /><Point T="0" X="990" Y="655" /><Point T="0" X="989" Y="687" /><Point T="0" X="1012" Y="608" /><Point T="0" X="1011" Y="592" /><Point T="0" X="1006" Y="662" /><Point T="0" X="1015" Y="714" /><Point T="0" X="1009" Y="761" /><Point T="0" X="1009" Y="799" /><Point T="0" X="1012" Y="800" /></Gesture>