<Gesture Name="zigzag"><Point T="0" X="752" Y="1062" /><Point T="0" X="752" Y="1040" /><Point T="0" X="747" Y="1019" /><Point T="0" X="752" Y="1036" /><Point T="0" X="761" Y="1057" /><Point T="0" X="754" Y="1036" /><Point T="0" X="750" Y="1057" /><Point T="0" X="750" Y="1057" /><Point T="0" X="532" Y="0" /><Point T="0" X="537" Y="0" /><Point T="0" X="548" Y="91" /><Point T="0" X="513" Y="73" /><Point T="0" X="547" Y="61" /><Point T="0" X="547" Y="61" /><Point T="0" X="949" Y="472" /><Point T="0" X="888" Y="425" /><Point T="0" X="700" Y="212" /><Point T="0" X="761" Y="283" /><Point T="0" X="783" Y="531" /><Point T="0" X="785" Y="425" /><Point T="0" X="783" Y="495" /><Point T="0" X="774" Y="606" /><Point T="0" X="771" Y="678" /><Point T="0" X="762" Y="697" /><Point T="0" X="753" Y="755" /><Point T="0" X="756" Y="802" /><Point T="0" X="763" Y="774" /><Point T="0" X="760" Y="809" /><Point T="0" X="761" Y="842" /><Point T="0" X="761" Y="868" /><Point T="0" X="762" Y="867" /><Point T="0" X="763" Y="843" /><Point T="0" X="770" Y="823" /><Point T="0" X="770" Y="824" /><Point T="0" X="779" Y="840" /><Point T="0" X="771" Y="840" /><Point T="0" X="771" Y="840" /><Point T="0" X="957" Y="212" /><Point T="0" X="948" Y="142" /><Point T="0" X="958" Y="106" /><Point T="0" X="910" Y="85" /><Point T="0" X="896" Y="275" /><Point T="0" X="910" Y="404" /><Point T="0" X="908" Y="460" /><Point T="0" X="922" Y="409" /><Point T="0" X="945" Y="368" /><Point T="0" X="959" Y="350" /><Point T="0" X="973" Y="325" /><Point T="0" X="970" Y="361" /><Point T="0" X="968" Y="366" /></Gesture>