<Gesture Name="./xml/circle01.xml02.xml03.xml04.xml05"><Point T="0" X="481" Y="187" /><Point T="0" X="481" Y="187" /><Point T="0" X="784" Y="0" /><Point T="0" X="769" Y="0" /><Point T="0" X="749" Y="0" /><Point T="0" X="753" Y="0" /><Point T="0" X="743" Y="0" /><Point T="0" X="710" Y="0" /><Point T="0" X="710" Y="0" /><Point T="0" X="432" Y="124" /><Point T="0" X="432" Y="124" /><Point T="0" X="1043" Y="603" /><Point T="0" X="1132" Y="603" /><Point T="0" X="1247" Y="312" /><Point T="0" X="1176" Y="118" /><Point T="0" X="1154" Y="59" /><Point T="0" X="1084" Y="60" /><Point T="0" X="1034" Y="45" /><Point T="0" X="982" Y="36" /><Point T="0" X="942" Y="30" /><Point T="0" X="910" Y="26" /></Gesture>