<Gesture Name="star"><Point T="0" X="978" Y="453" /><Point T="0" X="946" Y="377" /><Point T="0" X="946" Y="377" /><Point T="0" X="732" Y="424" /><Point T="0" X="693" Y="283" /><Point T="0" X="657" Y="318" /><Point T="0" X="657" Y="318" /><Point T="0" X="548" Y="0" /><Point T="0" X="595" Y="0" /><Point T="0" X="633" Y="0" /><Point T="0" X="622" Y="0" /><Point T="0" X="633" Y="0" /><Point T="0" X="655" Y="0" /><Point T="0" X="655" Y="0" /><Point T="0" X="1149" Y="425" /><Point T="0" X="892" Y="0" /><Point T="0" X="920" Y="0" /><Point T="0" X="930" Y="157" /><Point T="0" X="935" Y="118" /><Point T="0" X="969" Y="94" /><Point T="0" X="982" Y="79" /><Point T="0" X="977" Y="67" /><Point T="0" X="961" Y="160" /><Point T="0" X="960" Y="161" /><Point T="0" X="959" Y="268" /><Point T="0" X="949" Y="244" /><Point T="0" X="946" Y="223" /><Point T="0" X="953" Y="206" /><Point T="0" X="967" Y="191" /><Point T="0" X="969" Y="210" /><Point T="0" X="974" Y="205" /><Point T="0" X="978" Y="199" /><Point T="0" X="979" Y="190" /><Point T="0" X="983" Y="183" /><Point T="0" X="986" Y="174" /><Point T="0" X="996" Y="176" /><Point T="0" X="983" Y="176" /><Point T="0" X="978" Y="176" /><Point T="0" X="978" Y="176" /><Point T="0" X="584" Y="1603" /><Point T="0" X="615" Y="509" /><Point T="0" X="615" Y="679" /><Point T="0" X="636" Y="736" /><Point T="0" X="672" Y="858" /><Point T="0" X="747" Y="856" /><Point T="0" X="747" Y="856" /><Point T="0" X="1060" Y="116" /><Point T="0" X="1056" Y="247" /><Point T="0" X="1068" Y="312" /><Point T="0" X="1056" Y="250" /><Point T="0" X="1055" Y="288" /><Point T="0" X="1070" Y="261" /><Point T="0" X="1075" Y="228" /><Point T="0" X="1074" Y="203" /><Point T="0" X="1077" Y="182" /><Point T="0" X="1058" Y="215" /><Point T="0" X="1058" Y="215" /><Point T="0" X="582" Y="849" /><Point T="0" X="625" Y="836" /><Point T="0" X="662" Y="754" /><Point T="0" X="691" Y="773" /><Point T="0" X="711" Y="786" /><Point T="0" X="716" Y="741" /><Point T="0" X="735" Y="755" /></Gesture>