<Gesture Name="arrow"><Point T="0" X="728" Y="880" /><Point T="0" X="632" Y="744" /><Point T="0" X="611" Y="767" /><Point T="0" X="592" Y="764" /><Point T="0" X="554" Y="763" /><Point T="0" X="545" Y="762" /><Point T="0" X="526" Y="1033" /><Point T="0" X="526" Y="1033" /><Point T="0" X="1008" Y="1023" /><Point T="0" X="981" Y="967" /><Point T="0" X="968" Y="878" /><Point T="0" X="968" Y="873" /><Point T="0" X="968" Y="854" /><Point T="0" X="968" Y="840" /><Point T="0" X="963" Y="867" /><Point T="0" X="970" Y="855" /><Point T="0" X="966" Y="845" /><Point T="0" X="966" Y="821" /><Point T="0" X="958" Y="805" /><Point T="0" X="948" Y="777" /><Point T="0" X="948" Y="777" /><Point T="0" X="378" Y="2603" /><Point T="0" X="281" Y="2649" /><Point T="0" X="281" Y="2649" /><Point T="0" X="1014" Y="968" /><Point T="0" X="984" Y="897" /><Point T="0" X="980" Y="960" /><Point T="0" X="971" Y="920" /><Point T="0" X="971" Y="920" /><Point T="0" X="397" Y="2986" /><Point T="0" X="462" Y="2536" /><Point T="0" X="462" Y="2536" /><Point T="0" X="994" Y="1242" /><Point T="0" X="952" Y="1211" /></Gesture>