<Gesture Name="./xml/left_curly_brace01.xml02.xml03.xml04.xml05.xml06.xml07.xml08"><Point T="0" X="795" Y="474" /><Point T="0" X="782" Y="416" /><Point T="0" X="805" Y="406" /><Point T="0" X="812" Y="400" /><Point T="0" X="789" Y="368" /><Point T="0" X="772" Y="369" /><Point T="0" X="757" Y="369" /><Point T="0" X="743" Y="378" /><Point T="0" X="731" Y="403" /><Point T="0" X="723" Y="437" /><Point T="0" X="723" Y="437" /><Point T="0" X="533" Y="340" /><Point T="0" X="516" Y="379" /><Point T="0" X="507" Y="448" /><Point T="0" X="512" Y="450" /><Point T="0" X="502" Y="451" /><Point T="0" X="518" Y="460" /><Point T="0" X="510" Y="441" /><Point T="0" X="507" Y="478" /><Point T="0" X="499" Y="476" /><Point T="0" X="502" Y="461" /><Point T="0" X="487" Y="439" /><Point T="0" X="495" Y="440" /><Point T="0" X="509" Y="464" /><Point T="0" X="520" Y="464" /><Point T="0" X="520" Y="464" /><Point T="0" X="780" Y="862" /><Point T="0" X="771" Y="833" /><Point T="0" X="759" Y="862" /><Point T="0" X="756" Y="920" /><Point T="0" X="774" Y="925" /><Point T="0" X="783" Y="957" /><Point T="0" X="796" Y="956" /><Point T="0" X="807" Y="955" /><Point T="0" X="809" Y="955" /><Point T="0" X="808" Y="961" /><Point T="0" X="803" Y="945" /><Point T="0" X="809" Y="949" /></Gesture>