<Gesture Name="right_curly_brace"><Point T="0" X="903" Y="686" /><Point T="0" X="898" Y="649" /><Point T="0" X="892" Y="608" /><Point T="0" X="884" Y="579" /><Point T="0" X="878" Y="546" /><Point T="0" X="876" Y="518" /><Point T="0" X="870" Y="492" /><Point T="0" X="865" Y="448" /><Point T="0" X="862" Y="402" /><Point T="0" X="862" Y="402" /><Point T="0" X="764" Y="0" /><Point T="0" X="764" Y="0" /><Point T="0" X="1187" Y="223" /><Point T="0" X="926" Y="301" /><Point T="0" X="926" Y="318" /><Point T="0" X="1075" Y="286" /><Point T="0" X="1116" Y="327" /><Point T="0" X="1096" Y="347" /><Point T="0" X="1133" Y="403" /><Point T="0" X="1147" Y="479" /><Point T="0" X="1147" Y="479" /><Point T="0" X="1384" Y="612" /><Point T="0" X="1332" Y="640" /><Point T="0" X="1295" Y="654" /><Point T="0" X="1246" Y="634" /><Point T="0" X="1199" Y="621" /><Point T="0" X="1196" Y="632" /><Point T="0" X="1194" Y="622" /><Point T="0" X="1183" Y="644" /><Point T="0" X="1164" Y="680" /><Point T="0" X="1148" Y="706" /><Point T="0" X="1133" Y="729" /><Point T="0" X="1133" Y="729" /><Point T="0" X="840" Y="824" /><Point T="0" X="781" Y="1005" /><Point T="0" X="871" Y="1005" /><Point T="0" X="898" Y="1005" /><Point T="0" X="849" Y="892" /><Point T="0" X="832" Y="928" /><Point T="0" X="840" Y="907" /><Point T="0" X="824" Y="866" /><Point T="0" X="831" Y="860" /><Point T="0" X="836" Y="856" /><Point T="0" X="856" Y="852" /></Gesture>