<Gesture Name="v"><Point T="0" X="499" Y="591" /><Point T="0" X="503" Y="624" /><Point T="0" X="511" Y="681" /><Point T="0" X="518" Y="689" /><Point T="0" X="521" Y="681" /><Point T="0" X="524" Y="745" /><Point T="0" X="517" Y="702" /><Point T="0" X="530" Y="721" /><Point T="0" X="535" Y="782" /><Point T="0" X="549" Y="841" /><Point T="0" X="558" Y="860" /><Point T="0" X="578" Y="884" /><Point T="0" X="597" Y="906" /><Point T="0" X="614" Y="906" /><Point T="0" X="629" Y="986" /><Point T="0" X="648" Y="1025" /><Point T="0" X="669" Y="1066" /><Point T="0" X="669" Y="1066" /><Point T="0" X="802" Y="212" /><Point T="0" X="786" Y="566" /><Point T="0" X="822" Y="424" /><Point T="0" X="843" Y="425" /><Point T="0" X="861" Y="425" /><Point T="0" X="865" Y="532" /><Point T="0" X="899" Y="466" /><Point T="0" X="886" Y="550" /><Point T="0" X="886" Y="618" /><Point T="0" X="885" Y="673" /><Point T="0" X="888" Y="656" /><Point T="0" X="892" Y="642" /><Point T="0" X="896" Y="684" /><Point T="0" X="895" Y="715" /><Point T="0" X="888" Y="723" /><Point T="0" X="882" Y="749" /></Gesture>