<Gesture Name="x"><Point T="0" X="685" Y="664" /><Point T="0" X="688" Y="664" /><Point T="0" X="701" Y="636" /><Point T="0" X="705" Y="623" /><Point T="0" X="717" Y="573" /><Point T="0" X="721" Y="583" /><Point T="0" X="720" Y="600" /><Point T="0" X="720" Y="600" /><Point T="0" X="909" Y="668" /><Point T="0" X="915" Y="590" /><Point T="0" X="876" Y="442" /><Point T="0" X="834" Y="354" /><Point T="0" X="821" Y="295" /><Point T="0" X="821" Y="295" /><Point T="0" X="492" Y="0" /><Point T="0" X="433" Y="193" /><Point T="0" X="417" Y="273" /><Point T="0" X="402" Y="321" /></Gesture>