<Gesture Name="zigzag"><Point T="0" X="867" Y="723" /><Point T="0" X="867" Y="723" /><Point T="0" X="415" Y="0" /><Point T="0" X="412" Y="116" /><Point T="0" X="403" Y="191" /><Point T="0" X="390" Y="222" /><Point T="0" X="382" Y="243" /><Point T="0" X="386" Y="235" /><Point T="0" X="365" Y="249" /><Point T="0" X="375" Y="223" /><Point T="0" X="380" Y="236" /><Point T="0" X="380" Y="252" /><Point T="0" X="372" Y="231" /><Point T="0" X="376" Y="213" /><Point T="0" X="376" Y="211" /><Point T="0" X="376" Y="209" /><Point T="0" X="376" Y="196" /><Point T="0" X="376" Y="194" /><Point T="0" X="388" Y="188" /><Point T="0" X="388" Y="188" /><Point T="0" X="398" Y="209" /><Point T="0" X="403" Y="226" /><Point T="0" X="403" Y="226" /><Point T="0" X="713" Y="183" /><Point T="0" X="713" Y="183" /><Point T="0" X="713" Y="242" /><Point T="0" X="691" Y="277" /><Point T="0" X="689" Y="273" /><Point T="0" X="692" Y="284" /><Point T="0" X="695" Y="300" /><Point T="0" X="690" Y="277" /><Point T="0" X="692" Y="258" /><Point T="0" X="694" Y="273" /><Point T="0" X="696" Y="279" /><Point T="0" X="697" Y="284" /><Point T="0" X="687" Y="265" /><Point T="0" X="688" Y="271" /><Point T="0" X="687" Y="284" /><Point T="0" X="686" Y="269" /><Point T="0" X="683" Y="259" /><Point T="0" X="683" Y="250" /><Point T="0" X="690" Y="262" /><Point T="0" X="696" Y="262" /><Point T="0" X="696" Y="288" /><Point T="0" X="699" Y="288" /><Point T="0" X="703" Y="285" /><Point T="0" X="712" Y="268" /><Point T="0" X="723" Y="260" /><Point T="0" X="729" Y="247" /><Point T="0" X="735" Y="244" /><Point T="0" X="744" Y="257" /><Point T="0" X="753" Y="265" /></Gesture>