<?xml version="1.0" encoding="utf-8"?>
<Gesture Name="check04"><Point X="129" Y="236.99998474121094"/><Point X="129" Y="239"/><Point X="130" Y="242"/><Point X="132.00003051757813" Y="245"/><Point X="133" Y="246"/><Point X="135" Y="250.00001525878906"/><Point X="137" Y="253.00001525878906"/><Point X="139" Y="255"/><Point X="141" Y="259"/><Point X="142" Y="261"/><Point X="142.99996948242188" Y="264"/><Point X="145" Y="266"/><Point X="145" Y="267"/><Point X="145" Y="268"/><Point X="145" Y="269"/><Point X="145" Y="270"/><Point X="157.00001525878906" Y="253.99998474121094"/><Point X="163.99998474121094" Y="243.99998474121094"/><Point X="174" Y="233.00001525878906"/><Point X="188.99998474121094" Y="215"/><Point X="199" Y="204"/><Point X="206" Y="194"/><Point X="210.99998474121094" Y="189"/><Point X="213.00001525878906" Y="184"/><Point X="214.00001525878906" Y="181"/><Point X="216.00001525878906" Y="180"/><Point X="217" Y="178"/><Point X="218" Y="177"/><Point X="220" Y="176"/><Point X="221" Y="175"/><Point X="222" Y="174"/><Point X="224" Y="172"/><Point X="226" Y="169"/><Point X="229" Y="166"/><Point X="230" Y="164"/><Point X="233" Y="163"/><Point X="234.99998474121094" Y="159"/><Point X="235.99998474121094" Y="159"/><Point X="235.99998474121094" Y="158"/></Gesture>