<Gesture Name="check"><Point T="0" X="500" Y="341" /><Point T="0" X="528" Y="352" /><Point T="0" X="545" Y="358" /><Point T="0" X="543" Y="334" /><Point T="0" X="541" Y="317" /><Point T="0" X="550" Y="325" /><Point T="0" X="574" Y="331" /><Point T="0" X="585" Y="353" /><Point T="0" X="589" Y="371" /><Point T="0" X="593" Y="386" /><Point T="0" X="600" Y="411" /><Point T="0" X="599" Y="385" /><Point T="0" X="604" Y="383" /><Point T="0" X="608" Y="372" /><Point T="0" X="610" Y="363" /><Point T="0" X="617" Y="362" /><Point T="0" X="624" Y="364" /><Point T="0" X="629" Y="370" /><Point T="0" X="648" Y="385" /><Point T="0" X="653" Y="388" /><Point T="0" X="661" Y="385" /><Point T="0" X="665" Y="390" /><Point T="0" X="672" Y="386" /><Point T="0" X="684" Y="393" /><Point T="0" X="695" Y="399" /><Point T="0" X="701" Y="388" /><Point T="0" X="696" Y="382" /><Point T="0" X="705" Y="363" /><Point T="0" X="715" Y="344" /><Point T="0" X="727" Y="316" /><Point T="0" X="738" Y="281" /><Point T="0" X="754" Y="279" /><Point T="0" X="766" Y="261" /><Point T="0" X="777" Y="250" /><Point T="0" X="790" Y="240" /><Point T="0" X="796" Y="222" /><Point T="0" X="805" Y="202" /><Point T="0" X="812" Y="178" /><Point T="0" X="817" Y="153" /><Point T="0" X="827" Y="137" /><Point T="0" X="842" Y="112" /><Point T="0" X="856" Y="88" /><Point T="0" X="865" Y="72" /><Point T="0" X="872" Y="55" /><Point T="0" X="880" Y="38" /><Point T="0" X="891" Y="29" /></Gesture>