<Gesture Name="circle"><Point T="0" X="843" Y="0" /><Point T="0" X="826" Y="0" /><Point T="0" X="812" Y="0" /><Point T="0" X="799" Y="0" /><Point T="0" X="785" Y="0" /><Point T="0" X="767" Y="0" /><Point T="0" X="767" Y="0" /><Point T="0" X="444" Y="0" /><Point T="0" X="474" Y="0" /><Point T="0" X="470" Y="0" /><Point T="0" X="451" Y="19" /><Point T="0" X="465" Y="16" /><Point T="0" X="464" Y="14" /><Point T="0" X="456" Y="12" /><Point T="0" X="456" Y="16" /><Point T="0" X="464" Y="36" /><Point T="0" X="470" Y="60" /><Point T="0" X="475" Y="73" /><Point T="0" X="480" Y="80" /><Point T="0" X="487" Y="78" /><Point T="0" X="490" Y="93" /><Point T="0" X="488" Y="98" /><Point T="0" X="492" Y="103" /><Point T="0" X="492" Y="114" /><Point T="0" X="490" Y="134" /><Point T="0" X="489" Y="145" /><Point T="0" X="494" Y="169" /><Point T="0" X="501" Y="187" /><Point T="0" X="507" Y="211" /><Point T="0" X="514" Y="229" /><Point T="0" X="524" Y="235" /><Point T="0" X="527" Y="245" /><Point T="0" X="537" Y="270" /><Point T="0" X="547" Y="294" /><Point T="0" X="555" Y="310" /><Point T="0" X="565" Y="314" /><Point T="0" X="572" Y="310" /><Point T="0" X="584" Y="308" /><Point T="0" X="590" Y="324" /><Point T="0" X="597" Y="339" /><Point T="0" X="611" Y="348" /><Point T="0" X="630" Y="364" /><Point T="0" X="647" Y="380" /><Point T="0" X="667" Y="389" /><Point T="0" X="687" Y="389" /><Point T="0" X="704" Y="396" /><Point T="0" X="724" Y="380" /><Point T="0" X="740" Y="380" /><Point T="0" X="755" Y="378" /><Point T="0" X="772" Y="375" /><Point T="0" X="786" Y="382" /><Point T="0" X="799" Y="385" /><Point T="0" X="816" Y="383" /><Point T="0" X="816" Y="383" /><Point T="0" X="1000" Y="244" /><Point T="0" X="996" Y="204" /><Point T="0" X="988" Y="229" /><Point T="0" X="989" Y="245" /><Point T="0" X="984" Y="224" /><Point T="0" X="975" Y="192" /><Point T="0" X="978" Y="183" /><Point T="0" X="980" Y="168" /><Point T="0" X="986" Y="151" /><Point T="0" X="994" Y="137" /><Point T="0" X="994" Y="126" /><Point T="0" X="992" Y="116" /><Point T="0" X="981" Y="108" /><Point T="0" X="972" Y="101" /><Point T="0" X="957" Y="94" /><Point T="0" X="941" Y="89" /><Point T="0" X="931" Y="84" /><Point T="0" X="921" Y="80" /><Point T="0" X="911" Y="76" /><Point T="0" X="893" Y="60" /><Point T="0" X="887" Y="51" /><Point T="0" X="875" Y="45" /><Point T="0" X="869" Y="30" /><Point T="0" X="858" Y="14" /><Point T="0" X="844" Y="8" /><Point T="0" X="832" Y="8" /><Point T="0" X="814" Y="2" /><Point T="0" X="796" Y="0" /><Point T="0" X="777" Y="0" /><Point T="0" X="758" Y="0" /><Point T="0" X="741" Y="0" /><Point T="0" X="723" Y="0" /><Point T="0" X="713" Y="0" /><Point T="0" X="706" Y="0" /><Point T="0" X="702" Y="0" /><Point T="0" X="701" Y="0" /><Point T="0" X="696" Y="0" /><Point T="0" X="694" Y="0" /><Point T="0" X="691" Y="0" /><Point T="0" X="687" Y="0" /></Gesture>