<Gesture Name="triangle"><Point T="0" X="952" Y="34" /><Point T="0" X="482" Y="126" /><Point T="0" X="532" Y="84" /><Point T="0" X="507" Y="63" /><Point T="0" X="497" Y="93" /><Point T="0" X="494" Y="165" /><Point T="0" X="504" Y="211" /><Point T="0" X="507" Y="190" /><Point T="0" X="507" Y="193" /><Point T="0" X="502" Y="195" /><Point T="0" X="501" Y="177" /><Point T="0" X="501" Y="192" /><Point T="0" X="503" Y="194" /><Point T="0" X="500" Y="195" /><Point T="0" X="499" Y="196" /><Point T="0" X="501" Y="197" /><Point T="0" X="491" Y="186" /><Point T="0" X="486" Y="178" /><Point T="0" X="484" Y="171" /><Point T="0" X="482" Y="167" /><Point T="0" X="482" Y="160" /><Point T="0" X="484" Y="160" /><Point T="0" X="475" Y="169" /><Point T="0" X="476" Y="179" /><Point T="0" X="474" Y="179" /><Point T="0" X="473" Y="158" /><Point T="0" X="473" Y="144" /><Point T="0" X="476" Y="147" /><Point T="0" X="476" Y="147" /><Point T="0" X="922" Y="260" /><Point T="0" X="929" Y="275" /><Point T="0" X="933" Y="260" /><Point T="0" X="956" Y="306" /><Point T="0" X="978" Y="297" /><Point T="0" X="999" Y="269" /><Point T="0" X="1014" Y="267" /><Point T="0" X="1026" Y="265" /><Point T="0" X="1040" Y="252" /><Point T="0" X="1048" Y="232" /><Point T="0" X="1048" Y="220" /><Point T="0" X="1056" Y="203" /><Point T="0" X="1059" Y="189" /><Point T="0" X="1065" Y="176" /><Point T="0" X="1064" Y="165" /><Point T="0" X="1065" Y="164" /><Point T="0" X="1073" Y="154" /><Point T="0" X="1074" Y="146" /><Point T="0" X="1067" Y="139" /><Point T="0" X="1067" Y="139" /><Point T="0" X="680" Y="0" /><Point T="0" X="634" Y="0" /><Point T="0" X="611" Y="0" /><Point T="0" X="604" Y="0" /><Point T="0" X="681" Y="0" /><Point T="0" X="658" Y="0" /><Point T="0" X="625" Y="0" /><Point T="0" X="632" Y="0" /><Point T="0" X="656" Y="0" /><Point T="0" X="660" Y="0" /><Point T="0" X="663" Y="0" /><Point T="0" X="659" Y="0" /><Point T="0" X="653" Y="0" /></Gesture>